.gitignore
MANIFEST.in
README.txt
bootstrap.py
buildout.cfg
setup.cfg
setup.py
docs/HISTORY.txt
docs/INSTALL.txt
docs/LICENSE.GPL
docs/LICENSE.txt
src/collective/__init__.py
src/collective.calendarview.egg-info/PKG-INFO
src/collective.calendarview.egg-info/SOURCES.txt
src/collective.calendarview.egg-info/dependency_links.txt
src/collective.calendarview.egg-info/entry_points.txt
src/collective.calendarview.egg-info/namespace_packages.txt
src/collective.calendarview.egg-info/not-zip-safe
src/collective.calendarview.egg-info/requires.txt
src/collective.calendarview.egg-info/top_level.txt
src/collective/calendarview/__init__.py
src/collective/calendarview/browser.py
src/collective/calendarview/calendar.pt
src/collective/calendarview/configure.zcml
src/collective/calendarview/testing.py
src/collective/calendarview/testing.zcml
src/collective/calendarview/tests.py
src/collective/calendarview/profiles/default/cssregistry.xml
src/collective/calendarview/profiles/default/jsregistry.xml
src/collective/calendarview/profiles/default/metadata.xml
src/collective/calendarview/profiles/default/types/Folder.xml
src/collective/calendarview/static/calendarview.css
src/collective/calendarview/static/calendarview.js
src/collective/calendarview/static/calendarview_init.js