Metadata-Version: 1.1
Name: collective.calendarview
Version: 1.0
Summary: Fullcalendar view
Home-page: http://svn.plone.org/svn/collective/
Author: UNKNOWN
Author-email: UNKNOWN
License: GPL
Platform: UNKNOWN
Classifier: Framework :: Plone
Classifier: Programming Language :: Python
